{
  "name": "odse-connector",
  "config": {
    "connector.class": "io.debezium.connector.sqlserver.SqlServerConnector",
    "database.hostname": "rtr-mssql",
    "database.port": "1433",
    "database.user": "sa",
    "database.password": "PizzaIsGood33!",
    "database.dbname": "nbs_odse",
    "database.names": "nbs_odse",
    "database.server.name": "odse",
    "database.history.kafka.bootstrap.servers": "kafka:29092",
    "database.history.kafka.topic": "odse.history",
    "database.trustServerCertificate": "true",
    "include.schema.changes": "true",
    "key.converter": "org.apache.kafka.connect.json.JsonConverter",
    "key.converter.schemas.enable": "true",
    "producer.max.request.size": "10000000",
    "producer.message.max.bytes": "10000000",
    "snapshot.mode": "schema_only",
    "schema.history.internal.kafka.topic": "odse-schema-history",
    "schema.history.internal.kafka.bootstrap.servers": "kafka:29092",
    "table.include.list": "dbo.Person,dbo.Organization,dbo.Observation,dbo.Public_health_case,dbo.Treatment,dbo.state_defined_field_data,dbo.Notification,dbo.Interview,dbo.Place,dbo.CT_contact,dbo.Auth_user,dbo.Intervention,dbo.Act_relationship",
    "tasks.max": 1,
    "topic.prefix": "cdc",
    "topic.creation.default.replication.factor": 1,
    "topic.creation.default.partitions": 10,
    "topic.creation.default.cleanup.policy": "compact",
    "time.precision.mode": "connect",
    "transforms": "dropPrefix, convertTimezone",
    "transforms.dropPrefix.regex": "cdc\\.NBS_ODSE\\.dbo\\.(.+)",
    "transforms.dropPrefix.type": "org.apache.kafka.connect.transforms.RegexRouter",
    "transforms.dropPrefix.replacement": "nbs_$1",
    "transforms.convertTimezone.type": "io.debezium.transforms.TimezoneConverter",
    "transforms.convertTimezone.converted.timezone": "UTC",
    "value.converter": "org.apache.kafka.connect.json.JsonConverter",
    "value.converter.schemas.enable": "true"
  }
}
